daisy_sdk/__init__.py
daisy_sdk/auth.py
daisy_sdk/cli.py
daisy_sdk/image.py
daisy_sdk/utils.py
daisy_sdk-0.1.1.dist-info/licenses/LICENSE
daisy_sdk-0.1.1.dist-info/METADATA
daisy_sdk-0.1.1.dist-info/WHEEL
daisy_sdk-0.1.1.dist-info/entry_points.txt
daisy_sdk-0.1.1.dist-info/top_level.txt
daisy_sdk-0.1.1.dist-info/RECORD
