Metadata-Version: 2.4
Name: daisy-sdk
Version: 0.1.1
Summary: Daisy SDK CLI for auth and image fetch
Author: Daisy
License: MIT
Keywords: daisy,cli,sdk
Classifier: Programming Language :: Python :: 3
Classifier: Programming Language :: Python :: 3.11
Classifier: License :: OSI Approved :: MIT License
Requires-Python: >=3.11
License-File: LICENSE
Requires-Dist: requests<3.0,>=2.32
Requires-Dist: tomli-w<2.0,>=1.0
Requires-Dist: typer<1.0,>=0.12
Provides-Extra: dev
Requires-Dist: pytest<9,>=8; extra == "dev"
Dynamic: license-file
